aiur/__init__.py
aiur/main.py
aiur-0.0.0.dist-info/LICENSE
aiur-0.0.0.dist-info/METADATA
aiur-0.0.0.dist-info/WHEEL
aiur-0.0.0.dist-info/top_level.txt
aiur-0.0.0.dist-info/RECORD
